[{"name": "Travis Kelce", "position": "TE", "id": "26686", "rank": 1}, {"name": "Mark Andrews", "position": "TE", "id": "31056", "rank": 2}, {"name": "Zach Ertz", "position": "TE", "id": "26658", "rank": 3}, {"name": "Tyler Higbee", "position": "TE", "id": "29344", "rank": 4}, {"name": "Darren Waller", "position": "TE", "id": "28592", "rank": 5}, {"name": "Hunter Henry", "position": "TE", "id": "29269", "rank": 6}, {"name": "Jonnu Smith", "position": "TE", "id": "30213", "rank": 7}, {"name": "Mike Gesicki", "position": "TE", "id": "31012", "rank": 8}, {"name": "T.J. Hockenson", "position": "TE", "id": "31840", "rank": 9}, {"name": "Hayden Hurst", "position": "TE", "id": "30995", "rank": 10}, {"name": "Noah Fant", "position": "TE", "id": "31852", "rank": 11}, {"name": "Evan Engram", "position": "TE", "id": "30136", "rank": 12}, {"name": "Dalton Schultz", "position": "TE", "id": "31107", "rank": 13}, {"name": "Logan Thomas", "position": "TE", "id": "27648", "rank": 14}, {"name": "Jared Cook", "position": "TE", "id": "9353", "rank": 15}, {"name": "Austin Hooper", "position": "TE", "id": "29315", "rank": 16}, {"name": "Eric Ebron", "position": "TE", "id": "27538", "rank": 17}, {"name": "Drew Sample", "position": "TE", "id": "31884", "rank": 18}, {"name": "Jimmy Graham", "position": "TE", "id": "24070", "rank": 19}, {"name": "Chris Herndon IV", "position": "TE", "id": "31077", "rank": 20}, {"name": "Mo Alie-Cox", "position": "TE", "id": "30112", "rank": 21}, {"name": "Jordan Akins", "position": "TE", "id": "31068", "rank": 22}, {"name": "O.J. Howard", "position": "TE", "id": "30132", "rank": 23}, {"name": "Tyler Eifert", "position": "TE", "id": "26644", "rank": 24}, {"name": "Greg Olsen", "position": "TE", "id": "8285", "rank": 25}, {"name": "George Kittle", "position": "TE", "id": "30259", "rank": 26}, {"name": "Rob Gronkowski", "position": "TE", "id": "24017", "rank": 27}, {"name": "Jack Doyle", "position": "TE", "id": "27299", "rank": 28}, {"name": "Robert Tonyan", "position": "TE", "id": "30777", "rank": 29}, {"name": "Dan Arnold", "position": "TE", "id": "30891", "rank": 30}, {"name": "Irv Smith Jr.", "position": "TE", "id": "31882", "rank": 31}, {"name": "Darren Fells", "position": "TE", "id": "26612", "rank": 32}, {"name": "Anthony Firkser", "position": "TE", "id": "30571", "rank": 33}, {"name": "Kyle Rudolph", "position": "TE", "id": "24830", "rank": 34}, {"name": "Dawson Knox", "position": "TE", "id": "31928", "rank": 35}, {"name": "Ian Thomas", "position": "TE", "id": "31071", "rank": 36}, {"name": "Gerald Everett", "position": "TE", "id": "30157", "rank": 37}, {"name": "Nick Boyle", "position": "TE", "id": "28559", "rank": 38}, {"name": "Will Dissly", "position": "TE", "id": "31090", "rank": 39}, {"name": "Ryan Izzo", "position": "TE", "id": "31220", "rank": 40}, {"name": "Adam Trautman", "position": "TE", "id": "32775", "rank": 41}, {"name": "Cameron Brate", "position": "TE", "id": "28267", "rank": 42}, {"name": "Jace Sternberger", "position": "TE", "id": "31907", "rank": 43}, {"name": "Tyler Kroft", "position": "TE", "id": "28473", "rank": 44}, {"name": "Vance McDonald", "position": "TE", "id": "26678", "rank": 45}, {"name": "Ross Dwelley", "position": "TE", "id": "31329", "rank": 46}]